README.md
setup.py
marshmallow_extended/__init__.py
marshmallow_extended.egg-info/PKG-INFO
marshmallow_extended.egg-info/SOURCES.txt
marshmallow_extended.egg-info/dependency_links.txt
marshmallow_extended.egg-info/not-zip-safe
marshmallow_extended.egg-info/requires.txt
marshmallow_extended.egg-info/top_level.txt
marshmallow_extended/fields/__init__.py
marshmallow_extended/fields/active.py
marshmallow_extended/fields/email.py
marshmallow_extended/fields/enum.py
marshmallow_extended/fields/icontains.py
marshmallow_extended/fields/instance/__init__.py
marshmallow_extended/fields/instance/abstract_instance.py
marshmallow_extended/fields/instance/instance.py
marshmallow_extended/fields/instance/mongoengine_instance.py
marshmallow_extended/fields/instance/sqlalchemy_mixins_instance.py
marshmallow_extended/rest_api/__init__.py
marshmallow_extended/rest_api/decorators.py
marshmallow_extended/validate/__init__.py
marshmallow_extended/validate/not_blank.py
tests/__init__.py
tests/model.py
tests/test_case.py
tests/fields/__init__.py
tests/fields/active.py
tests/fields/datetime_filter.py
tests/fields/email_.py
tests/fields/instance.py